{
 "ok": true,
 "geo": "GB",
 "timeframe": "today 3-m",
 "data": {
  "Katie Loxton": {
   "latest": 4,
   "mean": 4.1,
   "series": [
    4,
    5,
    5,
    4,
    4,
    5,
    5,
    5,
    5,
    4,
    4,
    4,
    4
   ]
  },
  "Strathberry": {
   "latest": 4,
   "mean": 2.1,
   "series": [
    2,
    2,
    2,
    2,
    2,
    3,
    3,
    2,
    2,
    2,
    2,
    3,
    4
   ]
  },
  "DeMellier": {
   "latest": 100,
   "mean": 27.7,
   "series": [
    21,
    21,
    25,
    22,
    21,
    23,
    24,
    22,
    21,
    22,
    19,
    17,
    100
   ]
  },
  "Charles & Keith": {
   "latest": 0,
   "mean": 0.0,
   "series": [
    0,
    0,
    0,
    0,
    0,
    0,
    0,
    0,
    0,
    0,
    0,
    0,
    0
   ]
  },
  "Polene": {
   "latest": 5,
   "mean": 4.8,
   "series": [
    3,
    4,
    4,
    4,
    5,
    9,
    7,
    5,
    4,
    5,
    6,
    5,
    5
   ]
  },
  "Loewe": {
   "latest": 4,
   "mean": 4.1,
   "series": [
    3,
    3,
    3,
    4,
    4,
    4,
    4,
    3,
    3,
    3,
    3,
    4,
    4
   ]
  },
  "The White Company": {
   "latest": 5,
   "mean": 4.6,
   "series": [
    4,
    5,
    5,
    4,
    4,
    4,
    4,
    4,
    4,
    4,
    4,
    4,
    5
   ]
  },
  "Mejuri": {
   "latest": 0,
   "mean": 0.8,
   "series": [
    0,
    0,
    1,
    0,
    0,
    1,
    1,
    0,
    0,
    0,
    0,
    0,
    0
   ]
  },
  "Sezane": {
   "latest": 3,
   "mean": 3.1,
   "series": [
    2,
    2,
    2,
    2,
    2,
    3,
    3,
    2,
    2,
    2,
    2,
    2,
    3
   ]
  },
  "Coach": {
   "latest": 86,
   "mean": 81.1,
   "series": [
    88,
    90,
    87,
    82,
    79,
    93,
    94,
    88,
    86,
    95,
    84,
    82,
    86
   ]
  },
  "Oliver Bonas": {
   "latest": 54,
   "mean": 57.4,
   "series": [
    48,
    47,
    55,
    50,
    49,
    58,
    59,
    50,
    49,
    53,
    56,
    53,
    54
   ]
  },
  "Leo et Violette": {
   "latest": 0,
   "mean": 0.0,
   "series": [
    0,
    0,
    0,
    0,
    0,
    0,
    0,
    0,
    0,
    0,
    0,
    0,
    0
   ]
  },
  "Mint Velvet": {
   "latest": 47,
   "mean": 35.7,
   "series": [
    32,
    37,
    39,
    39,
    33,
    38,
    38,
    31,
    32,
    30,
    34,
    35,
    47
   ]
  }
 }
}